[
  {
    "id": "46B3A30F",
    "vendor_id": "V005",
    "name": "AR18X500HD-18\"X500' SILVER ALUM FOIL HEAVY DUTY 1/RL",
    "sku": "AAI-18FOILHD",
    "description": "",
    "category": "DELI SUPPLIES",
    "unit": "each",
    "pack_size": "18\"X500'",
    "cost": 0.0,
    "is_active": true,
    "image_url": "https://www.aaplastic.com/img.php?id=613303&s=S",
    "item_code": "613303"
  },
  {
    "id": "5A21EC59",
    "vendor_id": "V005",
    "name": "PUS910500-9\"X10.75\" SILVER POP UP FOIL 3000/CS 500/PK",
    "sku": "AAI-9POPFOIL",
    "description": "",
    "category": "DELI SUPPLIES",
    "unit": "each",
    "pack_size": "9\"X10.75\"",
    "cost": 0.0,
    "is_active": true,
    "image_url": "https://www.aaplastic.com/img.php?id=613300&s=S",
    "item_code": "613300"
  },
  {
    "id": "0AF24909",
    "vendor_id": "V005",
    "name": "114604-1 GL JR CONC DEGREASER 1/EA",
    "sku": "AFL-1364",
    "description": "",
    "category": "DELI SUPPLIES",
    "unit": "each",
    "pack_size": "1 GL",
    "cost": 0.0,
    "is_active": true,
    "image_url": "https://www.aaplastic.com/img.php?id=282006&s=S",
    "item_code": "282006"
  },
  {
    "id": "B8701E2F",
    "vendor_id": "V005",
    "name": "180904-1 GL LIQUID DISH DETERGENT 1/EA",
    "sku": "AFL-65026",
    "description": "",
    "category": "DELI SUPPLIES",
    "unit": "each",
    "pack_size": "1 GL",
    "cost": 0.0,
    "is_active": true,
    "image_url": "https://www.aaplastic.com/img.php?id=282013&s=S",
    "item_code": "282013"
  },
  {
    "id": "9D6B2400",
    "vendor_id": "V005",
    "name": "15044415-18\"X2000' CLEAR PLAST CUTTERBOX FILM 1/RL",
    "sku": "ANC-CW18X2",
    "description": "",
    "category": "DELI SUPPLIES",
    "unit": "each",
    "pack_size": "18\"X2000'",
    "cost": 0.0,
    "is_active": true,
    "image_url": "https://www.aaplastic.com/img.php?id=113015&s=S",
    "item_code": "113015"
  },
  {
    "id": "347AEE96",
    "vendor_id": "V005",
    "name": "4304002-8.85\"X6.41\"X1.10\" CLEAR ANTI-FOG DOME LID 252/CS",
    "sku": "ANC-LC4LD",
    "description": "",
    "category": "DELI SUPPLIES",
    "unit": "each",
    "pack_size": "8.85\"X6.41\"X1.10\"",
    "cost": 0.0,
    "is_active": true,
    "image_url": "https://www.aaplastic.com/img.php?id=104035&s=S",
    "item_code": "104035"
  },
  {
    "id": "0E56667A",
    "vendor_id": "V005",
    "name": "4541602-16 OZ BLACK RECTANGULAR MICRO CONT 252/CS",
    "sku": "ANC-M416B",
    "description": "",
    "category": "DELI SUPPLIES",
    "unit": "each",
    "pack_size": "16 OZ",
    "cost": 0.0,
    "is_active": true,
    "image_url": "https://www.aaplastic.com/img.php?id=104041&s=S",
    "item_code": "104041"
  },
  {
    "id": "D6067A5D",
    "vendor_id": "V005",
    "name": "11006755042-1 GL GROCERY BLEACH 6/CS",
    "sku": "BDW-2095",
    "description": "",
    "category": "DELI SUPPLIES",
    "unit": "each",
    "pack_size": "1 GL",
    "cost": 0.0,
    "is_active": true,
    "image_url": "https://www.aaplastic.com/img.php?id=136000&s=S",
    "item_code": "136000"
  },
  {
    "id": "6C888ACD",
    "vendor_id": "V005",
    "name": "BBQ-QUART-0.25 GL FOIL HOT FOOD BAG 1000/CS",
    "sku": "BRO-5B34",
    "description": "",
    "category": "DELI SUPPLIES",
    "unit": "each",
    "pack_size": "0.25 GL",
    "cost": 0.0,
    "is_active": true,
    "image_url": "https://www.aaplastic.com/img.php?id=122014&s=S",
    "item_code": "122014"
  },
  {
    "id": "14670812",
    "vendor_id": "V005",
    "name": "BBQ-HALF-0.5 GL RED/WHITE FOIL HOT FOOD BAG 500/CS",
    "sku": "BRO-5B36",
    "description": "",
    "category": "DELI SUPPLIES",
    "unit": "each",
    "pack_size": "0.5 GL",
    "cost": 0.0,
    "is_active": true,
    "image_url": "https://www.aaplastic.com/img.php?id=122015&s=S",
    "item_code": "122015"
  },
  {
    "id": "82C31D43",
    "vendor_id": "V005",
    "name": "98DLIDNH-98 MM CLEAR PET DOME LID NO HOLE 1000/CS",
    "sku": "CAB-98DLIDNH",
    "description": "",
    "category": "DELI SUPPLIES",
    "unit": "each",
    "pack_size": "98 MM",
    "cost": 0.0,
    "is_active": true,
    "image_url": "https://www.aaplastic.com/img.php?id=613441&s=S",
    "item_code": "613441"
  },
  {
    "id": "CC179C48",
    "vendor_id": "V005",
    "name": "IP-PPL-115- CLEAR PP PLASTIC SOUP LID 26-32 OZ 500/CS",
    "sku": "CAB-LGSLCLR",
    "description": "",
    "category": "DELI SUPPLIES",
    "unit": "each",
    "pack_size": "",
    "cost": 0.0,
    "is_active": true,
    "image_url": "https://www.aaplastic.com/img.php?id=613510&s=S",
    "item_code": "613510"
  },
  {
    "id": "8170AD4B",
    "vendor_id": "V005",
    "name": "LRGLID-3.25-5.5 OZ CLEAR PET PORTION LID 2500/CS",
    "sku": "CAB-LRGLID",
    "description": "",
    "category": "DELI SUPPLIES",
    "unit": "each",
    "pack_size": "3.25-5.5 OZ",
    "cost": 0.0,
    "is_active": true,
    "image_url": "https://www.aaplastic.com/img.php?id=613436&s=S",
    "item_code": "613436"
  },
  {
    "id": "CB1D8221",
    "vendor_id": "V005",
    "name": "MEDLID-1.5-2 OZ CLEAR PET PORTION LID 2500/CS",
    "sku": "CAB-MEDLID",
    "description": "",
    "category": "DELI SUPPLIES",
    "unit": "each",
    "pack_size": "1.5-2 OZ",
    "cost": 0.0,
    "is_active": true,
    "image_url": "https://www.aaplastic.com/img.php?id=613435&s=S",
    "item_code": "613435"
  },
  {
    "id": "F518B8F7",
    "vendor_id": "V005",
    "name": "P200-2 OZ CLEAR PP PORTION CUP 2500/CS",
    "sku": "CAB-P200",
    "description": "",
    "category": "DELI SUPPLIES",
    "unit": "each",
    "pack_size": "2 OZ",
    "cost": 0.0,
    "is_active": true,
    "image_url": "https://www.aaplastic.com/img.php?id=613426&s=S",
    "item_code": "613426"
  },
  {
    "id": "E766A4A2",
    "vendor_id": "V005",
    "name": "P400-4 OZ CLEAR PP PORTION CUP 2500/CS",
    "sku": "CAB-P400",
    "description": "",
    "category": "DELI SUPPLIES",
    "unit": "each",
    "pack_size": "4 OZ",
    "cost": 0.0,
    "is_active": true,
    "image_url": "https://www.aaplastic.com/img.php?id=613430&s=S",
    "item_code": "613430"
  },
  {
    "id": "0D2246A0",
    "vendor_id": "V005",
    "name": "IP-PSC16W-16 OZ WHITE PAPER SOUP CUP 500/CS",
    "sku": "CAB-W16SOUP",
    "description": "",
    "category": "DELI SUPPLIES",
    "unit": "each",
    "pack_size": "16 OZ",
    "cost": 0.0,
    "is_active": true,
    "image_url": "https://www.aaplastic.com/img.php?id=613513&s=S",
    "item_code": "613513"
  },
  {
    "id": "C4DC86A1",
    "vendor_id": "V005",
    "name": "IP-PSC32W-32 OZ WHITE PAPER SOUP CUP 500/CS",
    "sku": "CAB-W32SOUP",
    "description": "",
    "category": "DELI SUPPLIES",
    "unit": "each",
    "pack_size": "32 OZ",
    "cost": 0.0,
    "is_active": true,
    "image_url": "https://www.aaplastic.com/img.php?id=613515&s=S",
    "item_code": "613515"
  },
  {
    "id": "FE830728",
    "vendor_id": "V005",
    "name": "IP-PSC8W-8 OZ WHITE PAPER SOUP CUP 500/CS",
    "sku": "CAB-W8SOUP",
    "description": "",
    "category": "DELI SUPPLIES",
    "unit": "each",
    "pack_size": "8 OZ",
    "cost": 0.0,
    "is_active": true,
    "image_url": "https://www.aaplastic.com/img.php?id=613511&s=S",
    "item_code": "613511"
  },
  {
    "id": "4C139E30",
    "vendor_id": "V005",
    "name": "CL 00145-40\"X46\" 0.8 MIL CLEAR CAN LINER ON A RL 100/CS",
    "sku": "CL00145",
    "description": "",
    "category": "DELI SUPPLIES",
    "unit": "each",
    "pack_size": "40\"X46\"",
    "cost": 0.0,
    "is_active": true,
    "image_url": "https://www.aaplastic.com/img.php?id=412006&s=S",
    "item_code": "412006"
  },
  {
    "id": "78BCC7E0",
    "vendor_id": "V005",
    "name": "COL-9X9-9\"X9\" CLEAR 1 COMP PET HINGED CONT 200/CS",
    "sku": "COL-PET9X9",
    "description": "",
    "category": "DELI SUPPLIES",
    "unit": "each",
    "pack_size": "9\"X9\"",
    "cost": 0.0,
    "is_active": true,
    "image_url": "https://www.aaplastic.com/img.php?id=613564&s=S",
    "item_code": "613564"
  },
  {
    "id": "881722B1",
    "vendor_id": "V005",
    "name": "12PIZCIRCLE-12\" WHITE CAKE CIRCLE 100/CS",
    "sku": "CON-12",
    "description": "",
    "category": "DELI SUPPLIES",
    "unit": "each",
    "pack_size": "12\"",
    "cost": 0.0,
    "is_active": true,
    "image_url": "https://www.aaplastic.com/img.php?id=384006&s=S",
    "item_code": "384006"
  },
  {
    "id": "9D9BB6EF",
    "vendor_id": "V005",
    "name": "RPTTE12-12 OZ CLEAR PET HNDG TAMPER EVIDENT CONT 240/CS",
    "sku": "DIR-RPTTE12",
    "description": "",
    "category": "DELI SUPPLIES",
    "unit": "each",
    "pack_size": "12 OZ",
    "cost": 0.0,
    "is_active": true,
    "image_url": "https://www.aaplastic.com/img.php?id=613001&s=S",
    "item_code": "613001"
  },
  {
    "id": "1675685D",
    "vendor_id": "V005",
    "name": "RPTTE16N-16 OZ CLEAR HNDG TAMPER EVIDENT CONT 240/CS",
    "sku": "DIR-RPTTE16N",
    "description": "",
    "category": "DELI SUPPLIES",
    "unit": "each",
    "pack_size": "16 OZ",
    "cost": 0.0,
    "is_active": true,
    "image_url": "https://www.aaplastic.com/img.php?id=611906&s=S",
    "item_code": "611906"
  },
  {
    "id": "F9C65AC9",
    "vendor_id": "V005",
    "name": "RPTTE24-24 OZ CLEAR HNDG TAMPER EVIDENT CONT 200/CS",
    "sku": "DIR-RPTTE24",
    "description": "",
    "category": "DELI SUPPLIES",
    "unit": "each",
    "pack_size": "24 OZ",
    "cost": 0.0,
    "is_active": true,
    "image_url": "https://www.aaplastic.com/img.php?id=613006&s=S",
    "item_code": "613006"
  },
  {
    "id": "448F9DB5",
    "vendor_id": "V005",
    "name": "RPTTE32-32 OZ CLEAR HNDG TAMPER EVIDENT CONT 200/CS",
    "sku": "DIR-RPTTE32",
    "description": "",
    "category": "DELI SUPPLIES",
    "unit": "each",
    "pack_size": "32 OZ",
    "cost": 0.0,
    "is_active": true,
    "image_url": "https://www.aaplastic.com/img.php?id=613007&s=S",
    "item_code": "613007"
  },
  {
    "id": "C3731420",
    "vendor_id": "V005",
    "name": "RPTTE48SW-48 OZ CLEAR RPET HNDG TAMPER EVIDENT CONT 176/CS",
    "sku": "DIR-RPTTE48SW",
    "description": "",
    "category": "DELI SUPPLIES",
    "unit": "each",
    "pack_size": "48 OZ",
    "cost": 0.0,
    "is_active": true,
    "image_url": "https://www.aaplastic.com/img.php?id=614395&s=S",
    "item_code": "614395"
  },
  {
    "id": "993D4824",
    "vendor_id": "V005",
    "name": "RPTTE8-8 OZ CLEAR PET HNDG TAMPER EVIDENT CONT 240/CS",
    "sku": "DIR-RPTTE8",
    "description": "",
    "category": "DELI SUPPLIES",
    "unit": "each",
    "pack_size": "8 OZ",
    "cost": 0.0,
    "is_active": true,
    "image_url": "https://www.aaplastic.com/img.php?id=613000&s=S",
    "item_code": "613000"
  },
  {
    "id": "29AA928F",
    "vendor_id": "V005",
    "name": "1300-30-1.5 LB SILVER ALUM OBLONG SERVING TRAY 500/CS",
    "sku": "DPI-130030",
    "description": "",
    "category": "DELI SUPPLIES",
    "unit": "each",
    "pack_size": "1.5 LB",
    "cost": 0.0,
    "is_active": true,
    "image_url": "https://www.aaplastic.com/img.php?id=184006&s=S",
    "item_code": "184006"
  },
  {
    "id": "7EC5C6F7",
    "vendor_id": "V005",
    "name": "PM93-9\"X9\" WHITE MFPP HINGED CONTAINER 3 COMP 150/CS",
    "sku": "DRB-TC93",
    "description": "",
    "category": "DELI SUPPLIES",
    "unit": "each",
    "pack_size": "9\"X9\"",
    "cost": 0.0,
    "is_active": true,
    "image_url": "https://www.aaplastic.com/img.php?id=614368&s=S",
    "item_code": "614368"
  },
  {
    "id": "FB684F2A",
    "vendor_id": "V005",
    "name": "101417-18\"X5000' 50 GA CLEAR PLAST MEAT FILM 1/RL",
    "sku": "FPF-1850",
    "description": "",
    "category": "DELI SUPPLIES",
    "unit": "each",
    "pack_size": "18\"X5000'",
    "cost": 0.0,
    "is_active": true,
    "image_url": "https://www.aaplastic.com/img.php?id=611311&s=S",
    "item_code": "611311"
  },
  {
    "id": "28630C6E",
    "vendor_id": "V005",
    "name": "LDR-00018-2.25\"X4.5\" WHITE BLANK HOBART QUANTUM450 700/RL-16/CS",
    "sku": "GEO-HOB1097",
    "description": "",
    "category": "DELI SUPPLIES",
    "unit": "each",
    "pack_size": "2.25\"X4.5\"",
    "cost": 0.0,
    "is_active": true,
    "image_url": "https://www.aaplastic.com/img.php?id=610400&s=S",
    "item_code": "610400"
  },
  {
    "id": "503F7A79",
    "vendor_id": "V005",
    "name": "1002-1-4.5\" MULTI-COLORED TOOTHPICKS W/CLUB FRILLS 1000/CS",
    "sku": "GOL-10026",
    "description": "",
    "category": "DELI SUPPLIES",
    "unit": "each",
    "pack_size": "4.5\"",
    "cost": 0.0,
    "is_active": true,
    "image_url": "https://www.aaplastic.com/img.php?id=222001&s=S",
    "item_code": "222001"
  },
  {
    "id": "3677DE80",
    "vendor_id": "V005",
    "name": "5GFORK- BLACK PP H/W WRPD FORKS 1000/CS",
    "sku": "GOL-25701",
    "description": "",
    "category": "DELI SUPPLIES",
    "unit": "each",
    "pack_size": "",
    "cost": 0.0,
    "is_active": true,
    "image_url": "https://www.aaplastic.com/img.php?id=222046&s=S",
    "item_code": "222046"
  },
  {
    "id": "8B8EF7C3",
    "vendor_id": "V005",
    "name": "5GTSPOON- BLACK PP H/W WRPD TEA SPOONS 1000/CS",
    "sku": "GOL-25711",
    "description": "",
    "category": "DELI SUPPLIES",
    "unit": "each",
    "pack_size": "",
    "cost": 0.0,
    "is_active": true,
    "image_url": "https://www.aaplastic.com/img.php?id=222047&s=S",
    "item_code": "222047"
  },
  {
    "id": "CEA456B4",
    "vendor_id": "V005",
    "name": "PL042C-10.25\"X2.25\" SM 5-COMP PARTY PLATTER 100/CS",
    "sku": "INL-PL042C",
    "description": "",
    "category": "DELI SUPPLIES",
    "unit": "each",
    "pack_size": "10.25\"X2.25\"",
    "cost": 0.0,
    "is_active": true,
    "image_url": "https://www.aaplastic.com/img.php?id=240033&s=S",
    "item_code": "240033"
  },
  {
    "id": "E50C1A46",
    "vendor_id": "V005",
    "name": "VF8060-5\"X4\"X2\" CLEAR VISABLY FRESH IND CONT 330/CS",
    "sku": "INL-VF8060",
    "description": "",
    "category": "DELI SUPPLIES",
    "unit": "each",
    "pack_size": "5\"X4\"X2\"",
    "cost": 0.0,
    "is_active": true,
    "image_url": "https://www.aaplastic.com/img.php?id=240029&s=S",
    "item_code": "240029"
  },
  {
    "id": "6048A6F5",
    "vendor_id": "V005",
    "name": "902-000072-36\"X60' BLACK SURE GRIP LINER 1/EA",
    "sku": "KIT-13300K",
    "description": "",
    "category": "DELI SUPPLIES",
    "unit": "each",
    "pack_size": "36\"X60'",
    "cost": 0.0,
    "is_active": true,
    "image_url": "https://www.aaplastic.com/img.php?id=258001&s=S",
    "item_code": "258001"
  },
  {
    "id": "B89E0473",
    "vendor_id": "V005",
    "name": "1912-B-2.25\"X3.5\" HOBART QUANTUM PLAIN QWU350 16/CS 850/RL",
    "sku": "LBL-30088",
    "description": "",
    "category": "DELI SUPPLIES",
    "unit": "each",
    "pack_size": "2.25\"X3.5\"",
    "cost": 0.0,
    "is_active": true,
    "image_url": "https://www.aaplastic.com/img.php?id=250027&s=S",
    "item_code": "250027"
  },
  {
    "id": "FC782780",
    "vendor_id": "V005",
    "name": "C-KDL626-WH-98 MM CLEAR DOME W/H FOR 12-24 OZ CUPS 1000/CS",
    "sku": "LOL-CKDL626U",
    "description": "",
    "category": "DELI SUPPLIES",
    "unit": "each",
    "pack_size": "98 MM",
    "cost": 0.0,
    "is_active": true,
    "image_url": "https://www.aaplastic.com/img.php?id=611334&s=S",
    "item_code": "611334"
  },
  {
    "id": "9BB6BB4E",
    "vendor_id": "V005",
    "name": "C-KDL96-PP-6-16 OZ TRANSLUCENT PP FLAT LID VENTED 1000/CS",
    "sku": "LOL-CKDL96-PP",
    "description": "",
    "category": "DELI SUPPLIES",
    "unit": "each",
    "pack_size": "6-16 OZ",
    "cost": 0.0,
    "is_active": true,
    "image_url": "https://www.aaplastic.com/img.php?id=196012&s=S",
    "item_code": "196012"
  },
  {
    "id": "E232815A",
    "vendor_id": "V005",
    "name": "FP-GFC8W-8OZ WHITE PAPER SOUP CONTAINER 1000/CS",
    "sku": "LOL-SOUPCUP8",
    "description": "",
    "category": "DELI SUPPLIES",
    "unit": "each",
    "pack_size": "8OZ",
    "cost": 0.0,
    "is_active": true,
    "image_url": "https://www.aaplastic.com/img.php?id=613172&s=S",
    "item_code": "613172"
  },
  {
    "id": "DCB49628",
    "vendor_id": "V005",
    "name": "T-1506SW- WHITE #7 SHALLOW MEAT TRAY 300/CS",
    "sku": "MTC-7SW",
    "description": "",
    "category": "DELI SUPPLIES",
    "unit": "each",
    "pack_size": "",
    "cost": 0.0,
    "is_active": true,
    "image_url": "https://www.aaplastic.com/img.php?id=614090&s=S",
    "item_code": "614090"
  },
  {
    "id": "F6A5AE71",
    "vendor_id": "V005",
    "name": "DBNG104XL-XL BLACK NITRILE PF GLOVE 100/BX",
    "sku": "N-NITRILE-XL",
    "description": "",
    "category": "DELI SUPPLIES",
    "unit": "each",
    "pack_size": "XL",
    "cost": 0.0,
    "is_active": true,
    "image_url": "https://www.aaplastic.com/img.php?id=611069&s=S",
    "item_code": "611069"
  },
  {
    "id": "FE9F4C0C",
    "vendor_id": "V005",
    "name": "HOB1444-2.25\"X4.5\" KEILS HOBART QUANTUM 16/CS",
    "sku": "N-TH377KLS",
    "description": "",
    "category": "DELI SUPPLIES",
    "unit": "each",
    "pack_size": "2.25\"X4.5\"",
    "cost": 0.0,
    "is_active": true,
    "image_url": "https://www.aaplastic.com/img.php?id=262054&s=S",
    "item_code": "262054"
  },
  {
    "id": "7EB56560",
    "vendor_id": "V005",
    "name": "51200PK-12\" BLACK TRAY FLAT BASE 50/CS",
    "sku": "PAR-51201",
    "description": "",
    "category": "DELI SUPPLIES",
    "unit": "each",
    "pack_size": "12\"",
    "cost": 0.0,
    "is_active": true,
    "image_url": "https://www.aaplastic.com/img.php?id=366036&s=S",
    "item_code": "366036"
  },
  {
    "id": "980E5018",
    "vendor_id": "V005",
    "name": "51230-12\" CLEAR DOME LID FOR CATERING TRAY 50/CS",
    "sku": "PAR-51230",
    "description": "",
    "category": "DELI SUPPLIES",
    "unit": "each",
    "pack_size": "12\"",
    "cost": 0.0,
    "is_active": true,
    "image_url": "https://www.aaplastic.com/img.php?id=366026&s=S",
    "item_code": "366026"
  },
  {
    "id": "F321D95E",
    "vendor_id": "V005",
    "name": "51801-18\" BLACK TRAY FLAT BASE 50/CS",
    "sku": "PAR-51801",
    "description": "",
    "category": "DELI SUPPLIES",
    "unit": "each",
    "pack_size": "18\"",
    "cost": 0.0,
    "is_active": true,
    "image_url": "https://www.aaplastic.com/img.php?id=366038&s=S",
    "item_code": "366038"
  },
  {
    "id": "D4EC9D8C",
    "vendor_id": "V005",
    "name": "51840-18\" CLEAR DOME LID FOR CATERING TRAY 50/CS",
    "sku": "PAR-51840",
    "description": "",
    "category": "DELI SUPPLIES",
    "unit": "each",
    "pack_size": "18\"",
    "cost": 0.0,
    "is_active": true,
    "image_url": "https://www.aaplastic.com/img.php?id=366032&s=S",
    "item_code": "366032"
  },
  {
    "id": "45030482",
    "vendor_id": "V005",
    "name": "101423-18\"X1000' WHITE BUTCHER PAPER #40 1/EA",
    "sku": "PCT00110",
    "description": "",
    "category": "DELI SUPPLIES",
    "unit": "each",
    "pack_size": "18\"X1000'",
    "cost": 0.0,
    "is_active": true,
    "image_url": "https://www.aaplastic.com/img.php?id=312016&s=S",
    "item_code": "312016"
  },
  {
    "id": "3519DF04",
    "vendor_id": "V005",
    "name": "182169-16\"X16\" WHITE WAX PAPER 3000/CS",
    "sku": "PCT-16X16W",
    "description": "",
    "category": "DELI SUPPLIES",
    "unit": "each",
    "pack_size": "16\"X16\"",
    "cost": 0.0,
    "is_active": true,
    "image_url": "https://www.aaplastic.com/img.php?id=160003&s=S",
    "item_code": "160003"
  },
  {
    "id": "599BD98E",
    "vendor_id": "V005",
    "name": "9505466- CLEAR PP DELI LID 500/CS",
    "sku": "PLA-7037100",
    "description": "",
    "category": "DELI SUPPLIES",
    "unit": "each",
    "pack_size": "",
    "cost": 0.0,
    "is_active": true,
    "image_url": "https://www.aaplastic.com/img.php?id=326018&s=S",
    "item_code": "326018"
  },
  {
    "id": "940331A3",
    "vendor_id": "V005",
    "name": "9505102-16 OZ CLEAR ROUND DELI CONT 500/CS",
    "sku": "PLA-RD16C",
    "description": "",
    "category": "DELI SUPPLIES",
    "unit": "each",
    "pack_size": "16 OZ",
    "cost": 0.0,
    "is_active": true,
    "image_url": "https://www.aaplastic.com/img.php?id=326006&s=S",
    "item_code": "326006"
  },
  {
    "id": "2AA7A9DE",
    "vendor_id": "V005",
    "name": "9505104-32 OZ CLEAR ROUND DELI CONT 500/CS",
    "sku": "PLA-RD32C",
    "description": "",
    "category": "DELI SUPPLIES",
    "unit": "each",
    "pack_size": "32 OZ",
    "cost": 0.0,
    "is_active": true,
    "image_url": "https://www.aaplastic.com/img.php?id=326010&s=S",
    "item_code": "326010"
  },
  {
    "id": "EB826917",
    "vendor_id": "V005",
    "name": "9505100-8 OZ CLEAR ROUND DELI CONT 500/CS",
    "sku": "PLA-RD8C",
    "description": "",
    "category": "DELI SUPPLIES",
    "unit": "each",
    "pack_size": "8 OZ",
    "cost": 0.0,
    "is_active": true,
    "image_url": "https://www.aaplastic.com/img.php?id=326014&s=S",
    "item_code": "326014"
  },
  {
    "id": "3935AD1C",
    "vendor_id": "V005",
    "name": "K-10-10\"X10.75\" CLEAR CP10 H.D. PLASTIC INTERFOLD 10000/CS",
    "sku": "PPC-CP10",
    "description": "",
    "category": "DELI SUPPLIES",
    "unit": "each",
    "pack_size": "10\"X10.75\"",
    "cost": 0.0,
    "is_active": true,
    "image_url": "https://www.aaplastic.com/img.php?id=302013&s=S",
    "item_code": "302013"
  },
  {
    "id": "97A5D24C",
    "vendor_id": "V005",
    "name": "ST713B-7\"X13\" WHITE TALL FOLD VIRGIN NAP 10000/CS",
    "sku": "PPS-ST713B",
    "description": "",
    "category": "DELI SUPPLIES",
    "unit": "each",
    "pack_size": "7\"X13\"",
    "cost": 0.0,
    "is_active": true,
    "image_url": "https://www.aaplastic.com/img.php?id=314020&s=S",
    "item_code": "314020"
  },
  {
    "id": "F96B4AFC",
    "vendor_id": "V005",
    "name": "20800200- GREEN/YELLOW SCRUBBER SPONGE 5/PK",
    "sku": "PRM-25004166",
    "description": "",
    "category": "DELI SUPPLIES",
    "unit": "each",
    "pack_size": "",
    "cost": 0.0,
    "is_active": true,
    "image_url": "https://www.aaplastic.com/img.php?id=310046&s=S",
    "item_code": "310046"
  },
  {
    "id": "0092D7EC",
    "vendor_id": "V005",
    "name": "51P917S-17S BLACK FOAM MEAT TRAY 1000/BN",
    "sku": "PTV-17SK",
    "description": "",
    "category": "DELI SUPPLIES",
    "unit": "each",
    "pack_size": "17S",
    "cost": 0.0,
    "is_active": true,
    "image_url": "https://www.aaplastic.com/img.php?id=611957&s=S",
    "item_code": "611957"
  },
  {
    "id": "03CE1F91",
    "vendor_id": "V005",
    "name": "NM700-MED CLEAR VINYL GLOVES PWD FREE 10/CS 100/PK",
    "sku": "RVGPF102",
    "description": "",
    "category": "DELI SUPPLIES",
    "unit": "each",
    "pack_size": "MED",
    "cost": 0.0,
    "is_active": true,
    "image_url": "https://www.aaplastic.com/img.php?id=342010&s=S",
    "item_code": "342010"
  },
  {
    "id": "3756AB04",
    "vendor_id": "V005",
    "name": "NM700-LG CLEAR VINYL GLOVES PWD FREE 100/PK",
    "sku": "RVGPF103",
    "description": "",
    "category": "DELI SUPPLIES",
    "unit": "each",
    "pack_size": "LG",
    "cost": 0.0,
    "is_active": true,
    "image_url": "https://www.aaplastic.com/img.php?id=342011&s=S",
    "item_code": "342011"
  },
  {
    "id": "9B9C25A0",
    "vendor_id": "V005",
    "name": "NM700-XL CLEAR VINYL GLOVES PWD FREE 100/PK",
    "sku": "RVGPF104",
    "description": "",
    "category": "DELI SUPPLIES",
    "unit": "each",
    "pack_size": "XL",
    "cost": 0.0,
    "is_active": true,
    "image_url": "https://www.aaplastic.com/img.php?id=342012&s=S",
    "item_code": "342012"
  },
  {
    "id": "99E9D194",
    "vendor_id": "V005",
    "name": "10\"X8\" 1.3 MIL CLEAR PLAIN SLIDE SEAL TOP DELI BAG 1000/CS",
    "sku": "UNI-DELIBAG",
    "description": "",
    "category": "DELI SUPPLIES",
    "unit": "each",
    "pack_size": "10\"X8\"",
    "cost": 0.0,
    "is_active": true,
    "image_url": "https://www.aaplastic.com/img.php?id=196073&s=S",
    "item_code": "196073"
  },
  {
    "id": "EFDD000C",
    "vendor_id": "V005",
    "name": "434PB- STAINLESS STEEL SCRUBBER 12/PK 6/CS",
    "sku": "WES-77220",
    "description": "",
    "category": "DELI SUPPLIES",
    "unit": "each",
    "pack_size": "",
    "cost": 0.0,
    "is_active": true,
    "image_url": "https://www.aaplastic.com/img.php?id=310102&s=S",
    "item_code": "310102"
  },
  {
    "id": "SV-FZ-001",
    "vendor_id": "V006",
    "name": "Blount Clam Chowder Soup",
    "sku": "",
    "description": "",
    "category": "FROZEN",
    "unit": "each",
    "pack_size": "",
    "cost": 0.0,
    "is_active": true,
    "image_url": "",
    "item_code": ""
  },
  {
    "id": "SV-FZ-002",
    "vendor_id": "V006",
    "name": "Blount Chunky Chili Soup",
    "sku": "",
    "description": "",
    "category": "FROZEN",
    "unit": "each",
    "pack_size": "",
    "cost": 0.0,
    "is_active": true,
    "image_url": "",
    "item_code": ""
  },
  {
    "id": "SV-FZ-003",
    "vendor_id": "V006",
    "name": "Blount Baked Potato Soup",
    "sku": "",
    "description": "",
    "category": "FROZEN",
    "unit": "each",
    "pack_size": "",
    "cost": 0.0,
    "is_active": true,
    "image_url": "",
    "item_code": ""
  },
  {
    "id": "SV-FZ-004",
    "vendor_id": "V006",
    "name": "Blount Chicken Noodle Soup",
    "sku": "",
    "description": "",
    "category": "FROZEN",
    "unit": "each",
    "pack_size": "",
    "cost": 0.0,
    "is_active": true,
    "image_url": "",
    "item_code": ""
  },
  {
    "id": "SV-FZ-005",
    "vendor_id": "V006",
    "name": "Blount Broccoli Cheddar Soup",
    "sku": "",
    "description": "",
    "category": "FROZEN",
    "unit": "each",
    "pack_size": "",
    "cost": 0.0,
    "is_active": true,
    "image_url": "",
    "item_code": ""
  },
  {
    "id": "SV-FZ-006",
    "vendor_id": "V006",
    "name": "Blount Chicken Poblano Soup",
    "sku": "",
    "description": "",
    "category": "FROZEN",
    "unit": "each",
    "pack_size": "",
    "cost": 0.0,
    "is_active": true,
    "image_url": "",
    "item_code": ""
  },
  {
    "id": "SV-FZ-007",
    "vendor_id": "V006",
    "name": "Chicken Flautas",
    "sku": "",
    "description": "",
    "category": "FROZEN",
    "unit": "each",
    "pack_size": "",
    "cost": 0.0,
    "is_active": true,
    "image_url": "",
    "item_code": ""
  },
  {
    "id": "SV-FZ-008",
    "vendor_id": "V006",
    "name": "Corn Dogs",
    "sku": "",
    "description": "",
    "category": "FROZEN",
    "unit": "each",
    "pack_size": "",
    "cost": 0.0,
    "is_active": true,
    "image_url": "",
    "item_code": ""
  },
  {
    "id": "SV-FZ-009",
    "vendor_id": "V006",
    "name": "Egg Rolls",
    "sku": "",
    "description": "",
    "category": "FROZEN",
    "unit": "each",
    "pack_size": "",
    "cost": 0.0,
    "is_active": true,
    "image_url": "",
    "item_code": ""
  },
  {
    "id": "SV-FZ-010",
    "vendor_id": "V006",
    "name": "Poppers",
    "sku": "",
    "description": "",
    "category": "FROZEN",
    "unit": "each",
    "pack_size": "",
    "cost": 0.0,
    "is_active": true,
    "image_url": "",
    "item_code": ""
  },
  {
    "id": "SV-FZ-011",
    "vendor_id": "V006",
    "name": "Potato Wedges",
    "sku": "",
    "description": "",
    "category": "FROZEN",
    "unit": "each",
    "pack_size": "",
    "cost": 0.0,
    "is_active": true,
    "image_url": "",
    "item_code": ""
  },
  {
    "id": "SV-FZ-012",
    "vendor_id": "V006",
    "name": "Stouffers Mac and Cheese",
    "sku": "",
    "description": "",
    "category": "FROZEN",
    "unit": "each",
    "pack_size": "",
    "cost": 0.0,
    "is_active": true,
    "image_url": "",
    "item_code": ""
  },
  {
    "id": "SV-FZ-013",
    "vendor_id": "V006",
    "name": "Stouffers Mac and Beef",
    "sku": "",
    "description": "",
    "category": "FROZEN",
    "unit": "each",
    "pack_size": "",
    "cost": 0.0,
    "is_active": true,
    "image_url": "",
    "item_code": ""
  },
  {
    "id": "SV-FZ-014",
    "vendor_id": "V006",
    "name": "Stouffers Meatloaf",
    "sku": "",
    "description": "",
    "category": "FROZEN",
    "unit": "each",
    "pack_size": "",
    "cost": 0.0,
    "is_active": true,
    "image_url": "",
    "item_code": ""
  },
  {
    "id": "SV-FZ-015",
    "vendor_id": "V006",
    "name": "Stouffers Salisbury Steak",
    "sku": "",
    "description": "",
    "category": "FROZEN",
    "unit": "each",
    "pack_size": "",
    "cost": 0.0,
    "is_active": true,
    "image_url": "",
    "item_code": ""
  },
  {
    "id": "SV-FZ-016",
    "vendor_id": "V006",
    "name": "Stouffers Lasagna",
    "sku": "",
    "description": "",
    "category": "FROZEN",
    "unit": "each",
    "pack_size": "",
    "cost": 0.0,
    "is_active": true,
    "image_url": "",
    "item_code": ""
  },
  {
    "id": "SV-FZ-017",
    "vendor_id": "V006",
    "name": "Stouffers Stuffed Peppers",
    "sku": "",
    "description": "",
    "category": "FROZEN",
    "unit": "each",
    "pack_size": "",
    "cost": 0.0,
    "is_active": true,
    "image_url": "",
    "item_code": ""
  },
  {
    "id": "SV-FZ-018",
    "vendor_id": "V006",
    "name": "Stouffers Stuffed Cabbage",
    "sku": "",
    "description": "",
    "category": "FROZEN",
    "unit": "each",
    "pack_size": "",
    "cost": 0.0,
    "is_active": true,
    "image_url": "",
    "item_code": ""
  },
  {
    "id": "SV-FZ-019",
    "vendor_id": "V006",
    "name": "Stouffers Chicken Parmesan",
    "sku": "",
    "description": "",
    "category": "FROZEN",
    "unit": "each",
    "pack_size": "",
    "cost": 0.0,
    "is_active": true,
    "image_url": "",
    "item_code": ""
  },
  {
    "id": "SV-FZ-020",
    "vendor_id": "V006",
    "name": "Stouffers Beef Stew",
    "sku": "",
    "description": "",
    "category": "FROZEN",
    "unit": "each",
    "pack_size": "",
    "cost": 0.0,
    "is_active": true,
    "image_url": "",
    "item_code": ""
  },
  {
    "id": "SV-FZ-021",
    "vendor_id": "V006",
    "name": "Wings Barbecue",
    "sku": "",
    "description": "",
    "category": "FROZEN",
    "unit": "each",
    "pack_size": "",
    "cost": 0.0,
    "is_active": true,
    "image_url": "",
    "item_code": ""
  },
  {
    "id": "SV-FZ-022",
    "vendor_id": "V006",
    "name": "Wings Buffalo",
    "sku": "",
    "description": "",
    "category": "FROZEN",
    "unit": "each",
    "pack_size": "",
    "cost": 0.0,
    "is_active": true,
    "image_url": "",
    "item_code": ""
  },
  {
    "id": "SV-RF-001",
    "vendor_id": "V006",
    "name": "Cheese Basic White American",
    "sku": "",
    "description": "",
    "category": "REFRIGERATED",
    "unit": "each",
    "pack_size": "",
    "cost": 0.0,
    "is_active": true,
    "image_url": "",
    "item_code": ""
  },
  {
    "id": "SV-RF-002",
    "vendor_id": "V006",
    "name": "Strawberry Parfait",
    "sku": "",
    "description": "",
    "category": "REFRIGERATED",
    "unit": "each",
    "pack_size": "",
    "cost": 0.0,
    "is_active": true,
    "image_url": "",
    "item_code": ""
  },
  {
    "id": "SV-RF-003",
    "vendor_id": "V006",
    "name": "Orange Parfait",
    "sku": "",
    "description": "",
    "category": "REFRIGERATED",
    "unit": "each",
    "pack_size": "",
    "cost": 0.0,
    "is_active": true,
    "image_url": "",
    "item_code": ""
  },
  {
    "id": "SV-RF-004",
    "vendor_id": "V006",
    "name": "Deviled Egg Pot",
    "sku": "",
    "description": "",
    "category": "REFRIGERATED",
    "unit": "each",
    "pack_size": "",
    "cost": 0.0,
    "is_active": true,
    "image_url": "",
    "item_code": ""
  },
  {
    "id": "SV-RF-005",
    "vendor_id": "V006",
    "name": "Mustard Pot",
    "sku": "",
    "description": "",
    "category": "REFRIGERATED",
    "unit": "each",
    "pack_size": "",
    "cost": 0.0,
    "is_active": true,
    "image_url": "",
    "item_code": ""
  },
  {
    "id": "SV-RF-006",
    "vendor_id": "V006",
    "name": "Elbow Mac",
    "sku": "",
    "description": "",
    "category": "REFRIGERATED",
    "unit": "each",
    "pack_size": "",
    "cost": 0.0,
    "is_active": true,
    "image_url": "",
    "item_code": ""
  },
  {
    "id": "SV-RF-007",
    "vendor_id": "V006",
    "name": "Reg Pot",
    "sku": "",
    "description": "",
    "category": "REFRIGERATED",
    "unit": "each",
    "pack_size": "",
    "cost": 0.0,
    "is_active": true,
    "image_url": "",
    "item_code": ""
  },
  {
    "id": "SV-RF-008",
    "vendor_id": "V006",
    "name": "Blue Cheese and Bacon Pot",
    "sku": "",
    "description": "",
    "category": "REFRIGERATED",
    "unit": "each",
    "pack_size": "",
    "cost": 0.0,
    "is_active": true,
    "image_url": "",
    "item_code": ""
  },
  {
    "id": "SV-RF-009",
    "vendor_id": "V006",
    "name": "BBQ Beans",
    "sku": "",
    "description": "",
    "category": "REFRIGERATED",
    "unit": "each",
    "pack_size": "",
    "cost": 0.0,
    "is_active": true,
    "image_url": "",
    "item_code": ""
  },
  {
    "id": "SV-RF-010",
    "vendor_id": "V006",
    "name": "Four Bean",
    "sku": "",
    "description": "",
    "category": "REFRIGERATED",
    "unit": "each",
    "pack_size": "",
    "cost": 0.0,
    "is_active": true,
    "image_url": "",
    "item_code": ""
  },
  {
    "id": "SV-RF-011",
    "vendor_id": "V006",
    "name": "Jalapeño Mac",
    "sku": "",
    "description": "",
    "category": "REFRIGERATED",
    "unit": "each",
    "pack_size": "",
    "cost": 0.0,
    "is_active": true,
    "image_url": "",
    "item_code": ""
  },
  {
    "id": "SV-RF-012",
    "vendor_id": "V006",
    "name": "Mac and Cheddar",
    "sku": "",
    "description": "",
    "category": "REFRIGERATED",
    "unit": "each",
    "pack_size": "",
    "cost": 0.0,
    "is_active": true,
    "image_url": "",
    "item_code": ""
  },
  {
    "id": "SV-RF-013",
    "vendor_id": "V006",
    "name": "Chicken Caesar Pasta",
    "sku": "",
    "description": "",
    "category": "REFRIGERATED",
    "unit": "each",
    "pack_size": "",
    "cost": 0.0,
    "is_active": true,
    "image_url": "",
    "item_code": ""
  },
  {
    "id": "SV-RF-014",
    "vendor_id": "V006",
    "name": "Yoplait",
    "sku": "",
    "description": "",
    "category": "REFRIGERATED",
    "unit": "each",
    "pack_size": "",
    "cost": 0.0,
    "is_active": true,
    "image_url": "",
    "item_code": ""
  },
  {
    "id": "SV-MS-001",
    "vendor_id": "V006",
    "name": "Mr Pig Breading",
    "sku": "",
    "description": "",
    "category": "MISC",
    "unit": "each",
    "pack_size": "",
    "cost": 0.0,
    "is_active": true,
    "image_url": "",
    "item_code": ""
  },
  {
    "id": "OK-001",
    "vendor_id": "V007",
    "name": "Avocado 48Ct Prec MEX",
    "sku": "2040400",
    "description": "",
    "category": "PRODUCE",
    "unit": "each",
    "pack_size": "48Ct",
    "cost": 0.0,
    "is_active": true,
    "image_url": "",
    "item_code": ""
  },
  {
    "id": "OK-002",
    "vendor_id": "V007",
    "name": "Berry Blackberry 12/6Oz MEX/USA",
    "sku": "2280000",
    "description": "",
    "category": "PRODUCE",
    "unit": "each",
    "pack_size": "12/6Oz",
    "cost": 0.0,
    "is_active": true,
    "image_url": "",
    "item_code": ""
  },
  {
    "id": "OK-003",
    "vendor_id": "V007",
    "name": "Berry Blueberry 12/6Oz Peru",
    "sku": "2283700",
    "description": "",
    "category": "PRODUCE",
    "unit": "each",
    "pack_size": "12/6Oz",
    "cost": 0.0,
    "is_active": true,
    "image_url": "",
    "item_code": ""
  },
  {
    "id": "OK-004",
    "vendor_id": "V007",
    "name": "Berry Dris Raspberry 12/6Oz MEX/USA",
    "sku": "2282400",
    "description": "",
    "category": "PRODUCE",
    "unit": "each",
    "pack_size": "12/6Oz",
    "cost": 0.0,
    "is_active": true,
    "image_url": "",
    "item_code": ""
  },
  {
    "id": "OK-005",
    "vendor_id": "V007",
    "name": "Berry Dris Strw 8/1# USA/MEX",
    "sku": "2265700",
    "description": "",
    "category": "PRODUCE",
    "unit": "each",
    "pack_size": "8/1#",
    "cost": 0.0,
    "is_active": true,
    "image_url": "",
    "item_code": ""
  },
  {
    "id": "OK-006",
    "vendor_id": "V007",
    "name": "Berry Strawberry 8/1 USA/MEX",
    "sku": "2283000",
    "description": "",
    "category": "PRODUCE",
    "unit": "each",
    "pack_size": "8/1",
    "cost": 0.0,
    "is_active": true,
    "image_url": "",
    "item_code": ""
  },
  {
    "id": "OK-007",
    "vendor_id": "V007",
    "name": "Berry Strawberry Premium 8/1 USA/MEX",
    "sku": "2280800",
    "description": "",
    "category": "PRODUCE",
    "unit": "each",
    "pack_size": "8/1",
    "cost": 0.0,
    "is_active": true,
    "image_url": "",
    "item_code": ""
  },
  {
    "id": "OK-008",
    "vendor_id": "V007",
    "name": "Broccoli Crown 20# USA/MEX",
    "sku": "1060400",
    "description": "",
    "category": "PRODUCE",
    "unit": "each",
    "pack_size": "20#",
    "cost": 0.0,
    "is_active": true,
    "image_url": "",
    "item_code": ""
  },
  {
    "id": "OK-009",
    "vendor_id": "V007",
    "name": "Cabbage Grn Cello 45# USA",
    "sku": "1080400",
    "description": "",
    "category": "PRODUCE",
    "unit": "each",
    "pack_size": "45#",
    "cost": 0.0,
    "is_active": true,
    "image_url": "",
    "item_code": ""
  },
  {
    "id": "OK-010",
    "vendor_id": "V007",
    "name": "Carrot GF W/P Mini 15/2# USA",
    "sku": "1095800",
    "description": "",
    "category": "PRODUCE",
    "unit": "each",
    "pack_size": "15/2#",
    "cost": 0.0,
    "is_active": true,
    "image_url": "",
    "item_code": ""
  },
  {
    "id": "OK-011",
    "vendor_id": "V007",
    "name": "Carrot Shred 24/10Oz USA",
    "sku": "1092800",
    "description": "",
    "category": "PRODUCE",
    "unit": "each",
    "pack_size": "24/10Oz",
    "cost": 0.0,
    "is_active": true,
    "image_url": "",
    "item_code": ""
  },
  {
    "id": "OK-012",
    "vendor_id": "V007",
    "name": "Cauliflower 9Ct USA",
    "sku": "1100900",
    "description": "",
    "category": "PRODUCE",
    "unit": "each",
    "pack_size": "9Ct",
    "cost": 0.0,
    "is_active": true,
    "image_url": "",
    "item_code": ""
  },
  {
    "id": "OK-013",
    "vendor_id": "V007",
    "name": "Celery 30Ct Sleeved USA",
    "sku": "1110300",
    "description": "",
    "category": "PRODUCE",
    "unit": "each",
    "pack_size": "30Ct",
    "cost": 0.0,
    "is_active": true,
    "image_url": "",
    "item_code": ""
  },
  {
    "id": "OK-014",
    "vendor_id": "V007",
    "name": "Coleslaw Red/Cab Carrot 4/5# USA",
    "sku": "1082300",
    "description": "",
    "category": "PRODUCE",
    "unit": "each",
    "pack_size": "4/5#",
    "cost": 0.0,
    "is_active": true,
    "image_url": "",
    "item_code": ""
  },
  {
    "id": "OK-015",
    "vendor_id": "V007",
    "name": "Cucumber Hh 12Ct MEX",
    "sku": "1161400",
    "description": "",
    "category": "PRODUCE",
    "unit": "each",
    "pack_size": "12Ct",
    "cost": 0.0,
    "is_active": true,
    "image_url": "",
    "item_code": ""
  },
  {
    "id": "OK-016",
    "vendor_id": "V007",
    "name": "Grapes Black Sdls 18# Peru",
    "sku": "2110200",
    "description": "",
    "category": "PRODUCE",
    "unit": "each",
    "pack_size": "18#",
    "cost": 0.0,
    "is_active": true,
    "image_url": "",
    "item_code": ""
  },
  {
    "id": "OK-017",
    "vendor_id": "V007",
    "name": "Grapes Prem Green Sdls 18# Peru",
    "sku": "2112000",
    "description": "",
    "category": "PRODUCE",
    "unit": "each",
    "pack_size": "18#",
    "cost": 0.0,
    "is_active": true,
    "image_url": "",
    "item_code": ""
  },
  {
    "id": "OK-018",
    "vendor_id": "V007",
    "name": "Grapes Prem Red Sdls 18# Peru",
    "sku": "2114500",
    "description": "",
    "category": "PRODUCE",
    "unit": "each",
    "pack_size": "18#",
    "cost": 0.0,
    "is_active": true,
    "image_url": "",
    "item_code": ""
  },
  {
    "id": "OK-019",
    "vendor_id": "V007",
    "name": "Lettuce Cello 24Ct USA",
    "sku": "1272200",
    "description": "",
    "category": "PRODUCE",
    "unit": "each",
    "pack_size": "24Ct",
    "cost": 0.0,
    "is_active": true,
    "image_url": "",
    "item_code": ""
  },
  {
    "id": "OK-020",
    "vendor_id": "V007",
    "name": "Lettuce Green Lf 24Ct USA",
    "sku": "1271000",
    "description": "",
    "category": "PRODUCE",
    "unit": "each",
    "pack_size": "24Ct",
    "cost": 0.0,
    "is_active": true,
    "image_url": "",
    "item_code": ""
  },
  {
    "id": "OK-021",
    "vendor_id": "V007",
    "name": "Lettuce Romaine Chop 6/2# USA",
    "sku": "1271600",
    "description": "",
    "category": "PRODUCE",
    "unit": "each",
    "pack_size": "6/2#",
    "cost": 0.0,
    "is_active": true,
    "image_url": "",
    "item_code": ""
  },
  {
    "id": "OK-022",
    "vendor_id": "V007",
    "name": "Lettuce Shred 1/4\" 4/5# USA",
    "sku": "1270100",
    "description": "",
    "category": "PRODUCE",
    "unit": "each",
    "pack_size": "4/5#",
    "cost": 0.0,
    "is_active": true,
    "image_url": "",
    "item_code": ""
  },
  {
    "id": "OK-023",
    "vendor_id": "V007",
    "name": "Melon Cantaloupe 9Ct 35#",
    "sku": "2161500",
    "description": "",
    "category": "PRODUCE",
    "unit": "each",
    "pack_size": "9Ct 35#",
    "cost": 0.0,
    "is_active": true,
    "image_url": "",
    "item_code": ""
  },
  {
    "id": "OK-024",
    "vendor_id": "V007",
    "name": "Melon Honeydew 6Ct 25# MEX",
    "sku": "2161800",
    "description": "",
    "category": "PRODUCE",
    "unit": "each",
    "pack_size": "6Ct 25#",
    "cost": 0.0,
    "is_active": true,
    "image_url": "",
    "item_code": ""
  },
  {
    "id": "OK-025",
    "vendor_id": "V007",
    "name": "Melon Mini W-Melon 6Ct 35# MEX",
    "sku": "2162600",
    "description": "",
    "category": "PRODUCE",
    "unit": "each",
    "pack_size": "6Ct 35#",
    "cost": 0.0,
    "is_active": true,
    "image_url": "",
    "item_code": ""
  },
  {
    "id": "OK-026",
    "vendor_id": "V007",
    "name": "Mush Wht Bulk Lg 5# CAN",
    "sku": "1305600",
    "description": "",
    "category": "PRODUCE",
    "unit": "each",
    "pack_size": "5#",
    "cost": 0.0,
    "is_active": true,
    "image_url": "",
    "item_code": ""
  },
  {
    "id": "OK-027",
    "vendor_id": "V007",
    "name": "Onion Green 48Ct MEX Iceless",
    "sku": "1330600",
    "description": "",
    "category": "PRODUCE",
    "unit": "each",
    "pack_size": "48Ct",
    "cost": 0.0,
    "is_active": true,
    "image_url": "",
    "item_code": ""
  },
  {
    "id": "OK-028",
    "vendor_id": "V007",
    "name": "Onion Red Jbo 50# USA",
    "sku": "1333700",
    "description": "",
    "category": "PRODUCE",
    "unit": "each",
    "pack_size": "50#",
    "cost": 0.0,
    "is_active": true,
    "image_url": "",
    "item_code": ""
  },
  {
    "id": "OK-029",
    "vendor_id": "V007",
    "name": "ORG Broccoli Slaw 6/9Oz Bag Cal-O USA",
    "sku": "5020700",
    "description": "",
    "category": "PRODUCE",
    "unit": "each",
    "pack_size": "6/9Oz",
    "cost": 0.0,
    "is_active": true,
    "image_url": "",
    "item_code": ""
  },
  {
    "id": "OK-030",
    "vendor_id": "V007",
    "name": "ORG Sld Swt Spring Mix 3# USA/MEX",
    "sku": "1422800",
    "description": "",
    "category": "PRODUCE",
    "unit": "each",
    "pack_size": "3#",
    "cost": 0.0,
    "is_active": true,
    "image_url": "",
    "item_code": ""
  },
  {
    "id": "OK-031",
    "vendor_id": "V007",
    "name": "Pea Snow 10# USA",
    "sku": "1361000",
    "description": "",
    "category": "PRODUCE",
    "unit": "each",
    "pack_size": "10#",
    "cost": 0.0,
    "is_active": true,
    "image_url": "",
    "item_code": ""
  },
  {
    "id": "OK-032",
    "vendor_id": "V007",
    "name": "Pepper Bell Hh Orange 11# MEX",
    "sku": "1377000",
    "description": "",
    "category": "PRODUCE",
    "unit": "each",
    "pack_size": "11#",
    "cost": 0.0,
    "is_active": true,
    "image_url": "",
    "item_code": ""
  },
  {
    "id": "OK-033",
    "vendor_id": "V007",
    "name": "Pepper Bell Hh Red 11# MEX",
    "sku": "1376900",
    "description": "",
    "category": "PRODUCE",
    "unit": "each",
    "pack_size": "11#",
    "cost": 0.0,
    "is_active": true,
    "image_url": "",
    "item_code": ""
  },
  {
    "id": "OK-034",
    "vendor_id": "V007",
    "name": "Pepper Bell Hh Yell 11# MEX",
    "sku": "1371400",
    "description": "",
    "category": "PRODUCE",
    "unit": "each",
    "pack_size": "11#",
    "cost": 0.0,
    "is_active": true,
    "image_url": "",
    "item_code": ""
  },
  {
    "id": "OK-035",
    "vendor_id": "V007",
    "name": "Pineapple 5Ct Dole Costa Rica",
    "sku": "2255600",
    "description": "",
    "category": "PRODUCE",
    "unit": "each",
    "pack_size": "5Ct",
    "cost": 0.0,
    "is_active": true,
    "image_url": "",
    "item_code": ""
  },
  {
    "id": "OK-036",
    "vendor_id": "V007",
    "name": "Popeye Select Spinach 4/2.5# USA",
    "sku": "1440600",
    "description": "",
    "category": "PRODUCE",
    "unit": "each",
    "pack_size": "4/2.5#",
    "cost": 0.0,
    "is_active": true,
    "image_url": "",
    "item_code": ""
  },
  {
    "id": "OK-037",
    "vendor_id": "V007",
    "name": "Potato Gold Creamer 50# USA",
    "sku": "1386800",
    "description": "",
    "category": "PRODUCE",
    "unit": "each",
    "pack_size": "50#",
    "cost": 0.0,
    "is_active": true,
    "image_url": "",
    "item_code": ""
  },
  {
    "id": "OK-038",
    "vendor_id": "V007",
    "name": "Potato Red A 50lb USA",
    "sku": "1380700",
    "description": "",
    "category": "PRODUCE",
    "unit": "each",
    "pack_size": "50lb",
    "cost": 0.0,
    "is_active": true,
    "image_url": "",
    "item_code": ""
  },
  {
    "id": "OK-039",
    "vendor_id": "V007",
    "name": "Sprouts Bean 6/12Oz USA",
    "sku": "1452400",
    "description": "",
    "category": "PRODUCE",
    "unit": "each",
    "pack_size": "6/12Oz",
    "cost": 0.0,
    "is_active": true,
    "image_url": "",
    "item_code": ""
  },
  {
    "id": "OK-040",
    "vendor_id": "V007",
    "name": "TF Cabbage Red 6/8Oz",
    "sku": "1550800",
    "description": "",
    "category": "PRODUCE",
    "unit": "each",
    "pack_size": "6/8Oz",
    "cost": 0.0,
    "is_active": true,
    "image_url": "",
    "item_code": ""
  },
  {
    "id": "OK-041",
    "vendor_id": "V007",
    "name": "TF Sld Juicing Kale 6/16Oz USA/MEX",
    "sku": "1435000",
    "description": "",
    "category": "PRODUCE",
    "unit": "each",
    "pack_size": "6/16Oz",
    "cost": 0.0,
    "is_active": true,
    "image_url": "",
    "item_code": ""
  },
  {
    "id": "OK-042",
    "vendor_id": "V007",
    "name": "Tomato 4x5 2 Lyr 22# MEX",
    "sku": "1490400",
    "description": "",
    "category": "PRODUCE",
    "unit": "each",
    "pack_size": "22#",
    "cost": 0.0,
    "is_active": true,
    "image_url": "",
    "item_code": ""
  },
  {
    "id": "OK-043",
    "vendor_id": "V007",
    "name": "Tomato Loose 25# MEX",
    "sku": "1491800",
    "description": "",
    "category": "PRODUCE",
    "unit": "each",
    "pack_size": "25#",
    "cost": 0.0,
    "is_active": true,
    "image_url": "",
    "item_code": ""
  },
  {
    "id": "OK-044",
    "vendor_id": "V007",
    "name": "Tomato Roma 25# (Fs) MEX",
    "sku": "1494200",
    "description": "",
    "category": "PRODUCE",
    "unit": "each",
    "pack_size": "25#",
    "cost": 0.0,
    "is_active": true,
    "image_url": "",
    "item_code": ""
  }
]